rechtspraak_extractor/__init__.py
rechtspraak_extractor/_version.py
rechtspraak_extractor/rechtspraak.py
rechtspraak_extractor/rechtspraak_functions.py
rechtspraak_extractor/rechtspraak_metadata.py
rechtspraak_extractor-1.5.3.dist-info/licenses/LICENSE
rechtspraak_extractor-1.5.3.dist-info/METADATA
rechtspraak_extractor-1.5.3.dist-info/WHEEL
rechtspraak_extractor-1.5.3.dist-info/top_level.txt
rechtspraak_extractor-1.5.3.dist-info/RECORD
