Metadata-Version: 2.4
Name: rechtspraak_extractor
Version: 1.5.3
Summary: Library for extracting rechtspraak data
Author-email: LawTech Lab <law-techlab@maastrichtuniversity.nl>
License:                                  Apache License
Project-URL: Bug Tracker, https://github.com/maastrichtlawtech/rechtspraak-extractor/issues
Project-URL: Build Source, https://github.com/maastrichtlawtech/rechtspraak-extractor
Keywords: rechtspraak,extractor
Requires-Python: >=3.9
License-File: LICENSE
Requires-Dist: beautifulsoup4
Requires-Dist: bs4
Requires-Dist: certifi
Requires-Dist: charset-normalizer
Requires-Dist: idna
Requires-Dist: numpy
Requires-Dist: pandas
Requires-Dist: python-dateutil
Requires-Dist: pytz
Requires-Dist: requests
Requires-Dist: six
Requires-Dist: soupsieve
Requires-Dist: tqdm
Requires-Dist: typing_extensions
Requires-Dist: tzdata
Requires-Dist: urllib3
Requires-Dist: xmltodict
Requires-Dist: fake-headers
Requires-Dist: lxml
Dynamic: license-file
